[{"target":"Homer","weight":1,"x":-0.1221978926,"pair":["Abe","Homer"],"edge":0,"y":-0.1617551126,"source":"Abe"},{"target":"Homer","weight":1,"x":-0.4078190701,"pair":["Abe","Homer"],"edge":0,"y":-0.2133785126,"source":"Abe"},{"target":"Marge","weight":1,"x":-0.1221978926,"pair":["Abe","Marge"],"edge":1,"y":-0.1617551126,"source":"Abe"},{"target":"Marge","weight":1,"x":0.170799228,"pair":["Abe","Marge"],"edge":1,"y":-0.0904164774,"source":"Abe"},{"target":"Bart","weight":3,"x":-0.4078190701,"pair":["Homer","Bart"],"edge":2,"y":-0.2133785126,"source":"Homer"},{"target":"Bart","weight":3,"x":0.232808136,"pair":["Homer","Bart"],"edge":2,"y":0.4859211705,"source":"Homer"},{"target":"Charles","weight":2,"x":-0.4078190701,"pair":["Homer","Charles"],"edge":3,"y":-0.2133785126,"source":"Homer"},{"target":"Charles","weight":2,"x":-0.8554112714,"pair":["Homer","Charles"],"edge":3,"y":0.1022431083,"source":"Homer"},{"target":"Diner Cook","weight":1,"x":-0.4078190701,"pair":["Homer","Diner Cook"],"edge":4,"y":-0.2133785126,"source":"Homer"},{"target":"Diner Cook","weight":1,"x":-0.6735530404,"pair":["Homer","Diner Cook"],"edge":4,"y":-0.2667552504,"source":"Homer"},{"target":"Dr. Hibbert","weight":2,"x":-0.4078190701,"pair":["Homer","Dr. Hibbert"],"edge":5,"y":-0.2133785126,"source":"Homer"},{"target":"Dr. Hibbert","weight":2,"x":-0.6842248029,"pair":["Homer","Dr. Hibbert"],"edge":5,"y":-0.8172975661,"source":"Homer"},{"target":"Fat Tony","weight":1,"x":-0.4078190701,"pair":["Homer","Fat Tony"],"edge":6,"y":-0.2133785126,"source":"Homer"},{"target":"Fat Tony","weight":1,"x":-0.5905189773,"pair":["Homer","Fat Tony"],"edge":6,"y":-0.4168698114,"source":"Homer"},{"target":"Jimbo\/Dolph\/Kearney","weight":1,"x":-0.4078190701,"pair":["Homer","Jimbo\/Dolph\/Kearney"],"edge":7,"y":-0.2133785126,"source":"Homer"},{"target":"Jimbo\/Dolph\/Kearney","weight":1,"x":-0.4272338036,"pair":["Homer","Jimbo\/Dolph\/Kearney"],"edge":7,"y":-0.5060085389,"source":"Homer"},{"target":"Lisa","weight":5,"x":-0.4078190701,"pair":["Homer","Lisa"],"edge":8,"y":-0.2133785126,"source":"Homer"},{"target":"Lisa","weight":5,"x":0.7231527304,"pair":["Homer","Lisa"],"edge":8,"y":-0.5346928239,"source":"Homer"},{"target":"Marge","weight":9,"x":-0.4078190701,"pair":["Homer","Marge"],"edge":9,"y":-0.2133785126,"source":"Homer"},{"target":"Marge","weight":9,"x":0.170799228,"pair":["Homer","Marge"],"edge":9,"y":-0.0904164774,"source":"Homer"},{"target":"Patty","weight":1,"x":-0.4078190701,"pair":["Homer","Patty"],"edge":10,"y":-0.2133785126,"source":"Homer"},{"target":"Patty","weight":1,"x":-0.5635564709,"pair":["Homer","Patty"],"edge":10,"y":0.0422373335,"source":"Homer"},{"target":"Sideshow Bob","weight":1,"x":-0.4078190701,"pair":["Homer","Sideshow Bob"],"edge":11,"y":-0.2133785126,"source":"Homer"},{"target":"Sideshow Bob","weight":1,"x":-0.2827409498,"pair":["Homer","Sideshow Bob"],"edge":11,"y":-0.4538154855,"source":"Homer"},{"target":"Verity","weight":1,"x":-0.4078190701,"pair":["Homer","Verity"],"edge":12,"y":-0.2133785126,"source":"Homer"},{"target":"Verity","weight":1,"x":-0.6684573204,"pair":["Homer","Verity"],"edge":12,"y":-0.0743856409,"source":"Homer"},{"target":"Bart","weight":3,"x":0.170799228,"pair":["Marge","Bart"],"edge":13,"y":-0.0904164774,"source":"Marge"},{"target":"Bart","weight":3,"x":0.232808136,"pair":["Marge","Bart"],"edge":13,"y":0.4859211705,"source":"Marge"},{"target":"Lisa","weight":2,"x":0.170799228,"pair":["Marge","Lisa"],"edge":14,"y":-0.0904164774,"source":"Marge"},{"target":"Lisa","weight":2,"x":0.7231527304,"pair":["Marge","Lisa"],"edge":14,"y":-0.5346928239,"source":"Marge"},{"target":"Maid 1","weight":1,"x":0.170799228,"pair":["Marge","Maid 1"],"edge":15,"y":-0.0904164774,"source":"Marge"},{"target":"Maid 1","weight":1,"x":0.2190661607,"pair":["Marge","Maid 1"],"edge":15,"y":-0.3206478041,"source":"Marge"},{"target":"Maid 2","weight":1,"x":0.170799228,"pair":["Marge","Maid 2"],"edge":16,"y":-0.0904164774,"source":"Marge"},{"target":"Maid 2","weight":1,"x":0.3737909989,"pair":["Marge","Maid 2"],"edge":16,"y":-0.2963213474,"source":"Marge"},{"target":"Maids","weight":1,"x":0.170799228,"pair":["Marge","Maids"],"edge":17,"y":-0.0904164774,"source":"Marge"},{"target":"Maids","weight":1,"x":0.401681731,"pair":["Marge","Maids"],"edge":17,"y":-0.1374691437,"source":"Marge"},{"target":"Principal Skinner","weight":1,"x":0.170799228,"pair":["Marge","Principal Skinner"],"edge":18,"y":-0.0904164774,"source":"Marge"},{"target":"Principal Skinner","weight":1,"x":0.2273648636,"pair":["Marge","Principal Skinner"],"edge":18,"y":0.2003702197,"source":"Marge"},{"target":"Host","weight":1,"x":0.2146247414,"pair":["Announcer","Host"],"edge":19,"y":-0.0322779834,"source":"Announcer"},{"target":"Host","weight":1,"x":0.3521888313,"pair":["Announcer","Host"],"edge":19,"y":0.176853187,"source":"Announcer"},{"target":"Krusty","weight":1,"x":0.2146247414,"pair":["Announcer","Krusty"],"edge":20,"y":-0.0322779834,"source":"Announcer"},{"target":"Krusty","weight":1,"x":0.1022927831,"pair":["Announcer","Krusty"],"edge":20,"y":0.1914043991,"source":"Announcer"},{"target":"Krusty","weight":1,"x":0.3521888313,"pair":["Host","Krusty"],"edge":21,"y":0.176853187,"source":"Host"},{"target":"Krusty","weight":1,"x":0.1022927831,"pair":["Host","Krusty"],"edge":21,"y":0.1914043991,"source":"Host"},{"target":"Moe","weight":1,"x":0.2679392722,"pair":["Barney","Moe"],"edge":22,"y":0.0807166768,"source":"Barney"},{"target":"Moe","weight":1,"x":0.0961658636,"pair":["Barney","Moe"],"edge":22,"y":0.2627929737,"source":"Barney"},{"target":"Melanie Upfoot","weight":1,"x":0.232808136,"pair":["Bart","Melanie Upfoot"],"edge":23,"y":0.4859211705,"source":"Bart"},{"target":"Melanie Upfoot","weight":1,"x":0.5431669795,"pair":["Bart","Melanie Upfoot"],"edge":23,"y":0.5129003535,"source":"Bart"},{"target":"Milhouse","weight":1,"x":0.232808136,"pair":["Bart","Milhouse"],"edge":24,"y":0.4859211705,"source":"Bart"},{"target":"Milhouse","weight":1,"x":0.4190009111,"pair":["Bart","Milhouse"],"edge":24,"y":0.3230621764,"source":"Bart"},{"target":"Mr. Burns","weight":1,"x":0.232808136,"pair":["Bart","Mr. Burns"],"edge":25,"y":0.4859211705,"source":"Bart"},{"target":"Mr. Burns","weight":1,"x":0.2827343772,"pair":["Bart","Mr. Burns"],"edge":25,"y":0.7368874401,"source":"Bart"},{"target":"Mr. Largo","weight":1,"x":0.232808136,"pair":["Bart","Mr. Largo"],"edge":26,"y":0.4859211705,"source":"Bart"},{"target":"Mr. Largo","weight":1,"x":0.1392661588,"pair":["Bart","Mr. Largo"],"edge":26,"y":0.7893271938,"source":"Bart"},{"target":"Pilot","weight":1,"x":0.232808136,"pair":["Bart","Pilot"],"edge":27,"y":0.4859211705,"source":"Bart"},{"target":"Pilot","weight":1,"x":-0.0436779679,"pair":["Bart","Pilot"],"edge":27,"y":0.5377801927,"source":"Bart"},{"target":"Principal Skinner","weight":1,"x":0.232808136,"pair":["Bart","Principal Skinner"],"edge":28,"y":0.4859211705,"source":"Bart"},{"target":"Principal Skinner","weight":1,"x":0.2273648636,"pair":["Bart","Principal Skinner"],"edge":28,"y":0.2003702197,"source":"Bart"},{"target":"Smithers","weight":1,"x":0.232808136,"pair":["Bart","Smithers"],"edge":29,"y":0.4859211705,"source":"Bart"},{"target":"Smithers","weight":1,"x":0.0551845754,"pair":["Bart","Smithers"],"edge":29,"y":0.6796776934,"source":"Bart"},{"target":"Superintendent Chalmers","weight":1,"x":0.232808136,"pair":["Bart","Superintendent Chalmers"],"edge":30,"y":0.4859211705,"source":"Bart"},{"target":"Superintendent Chalmers","weight":1,"x":0.4733598583,"pair":["Bart","Superintendent Chalmers"],"edge":30,"y":0.6680217273,"source":"Bart"},{"target":"Superintendent Chalmers","weight":1,"x":0.5431669795,"pair":["Melanie Upfoot","Superintendent Chalmers"],"edge":31,"y":0.5129003535,"source":"Melanie Upfoot"},{"target":"Superintendent Chalmers","weight":1,"x":0.4733598583,"pair":["Melanie Upfoot","Superintendent Chalmers"],"edge":31,"y":0.6680217273,"source":"Melanie Upfoot"},{"target":"Principal Skinner","weight":1,"x":0.4190009111,"pair":["Milhouse","Principal Skinner"],"edge":32,"y":0.3230621764,"source":"Milhouse"},{"target":"Principal Skinner","weight":1,"x":0.2273648636,"pair":["Milhouse","Principal Skinner"],"edge":32,"y":0.2003702197,"source":"Milhouse"},{"target":"Smithers","weight":1,"x":0.2827343772,"pair":["Mr. Burns","Smithers"],"edge":33,"y":0.7368874401,"source":"Mr. Burns"},{"target":"Smithers","weight":1,"x":0.0551845754,"pair":["Mr. Burns","Smithers"],"edge":33,"y":0.6796776934,"source":"Mr. Burns"},{"target":"Comic Book Guy","weight":1,"x":-0.0006010186,"pair":["Benjamin","Comic Book Guy"],"edge":34,"y":0.1524914198,"source":"Benjamin"},{"target":"Comic Book Guy","weight":1,"x":-0.0585741428,"pair":["Benjamin","Comic Book Guy"],"edge":34,"y":0.3240998701,"source":"Benjamin"},{"target":"Doug","weight":1,"x":-0.0006010186,"pair":["Benjamin","Doug"],"edge":35,"y":0.1524914198,"source":"Benjamin"},{"target":"Doug","weight":1,"x":-0.23969868,"pair":["Benjamin","Doug"],"edge":35,"y":0.3219939392,"source":"Benjamin"},{"target":"Squeaky-Voiced Teen","weight":1,"x":-0.0006010186,"pair":["Benjamin","Squeaky-Voiced Teen"],"edge":36,"y":0.1524914198,"source":"Benjamin"},{"target":"Squeaky-Voiced Teen","weight":1,"x":-0.2936655447,"pair":["Benjamin","Squeaky-Voiced Teen"],"edge":36,"y":0.14908333,"source":"Benjamin"},{"target":"Willie","weight":1,"x":-0.0006010186,"pair":["Benjamin","Willie"],"edge":37,"y":0.1524914198,"source":"Benjamin"},{"target":"Willie","weight":1,"x":-0.1458944893,"pair":["Benjamin","Willie"],"edge":37,"y":0.0443257869,"source":"Benjamin"},{"target":"Doug","weight":1,"x":-0.0585741428,"pair":["Comic Book Guy","Doug"],"edge":38,"y":0.3240998701,"source":"Comic Book Guy"},{"target":"Doug","weight":1,"x":-0.23969868,"pair":["Comic Book Guy","Doug"],"edge":38,"y":0.3219939392,"source":"Comic Book Guy"},{"target":"Squeaky-Voiced Teen","weight":1,"x":-0.0585741428,"pair":["Comic Book Guy","Squeaky-Voiced Teen"],"edge":39,"y":0.3240998701,"source":"Comic Book Guy"},{"target":"Squeaky-Voiced Teen","weight":1,"x":-0.2936655447,"pair":["Comic Book Guy","Squeaky-Voiced Teen"],"edge":39,"y":0.14908333,"source":"Comic Book Guy"},{"target":"Willie","weight":1,"x":-0.0585741428,"pair":["Comic Book Guy","Willie"],"edge":40,"y":0.3240998701,"source":"Comic Book Guy"},{"target":"Willie","weight":1,"x":-0.1458944893,"pair":["Comic Book Guy","Willie"],"edge":40,"y":0.0443257869,"source":"Comic Book Guy"},{"target":"Squeaky-Voiced Teen","weight":1,"x":-0.23969868,"pair":["Doug","Squeaky-Voiced Teen"],"edge":41,"y":0.3219939392,"source":"Doug"},{"target":"Squeaky-Voiced Teen","weight":1,"x":-0.2936655447,"pair":["Doug","Squeaky-Voiced Teen"],"edge":41,"y":0.14908333,"source":"Doug"},{"target":"Willie","weight":1,"x":-0.23969868,"pair":["Doug","Willie"],"edge":42,"y":0.3219939392,"source":"Doug"},{"target":"Willie","weight":1,"x":-0.1458944893,"pair":["Doug","Willie"],"edge":42,"y":0.0443257869,"source":"Doug"},{"target":"Willie","weight":1,"x":-0.2936655447,"pair":["Squeaky-Voiced Teen","Willie"],"edge":43,"y":0.14908333,"source":"Squeaky-Voiced Teen"},{"target":"Willie","weight":1,"x":-0.1458944893,"pair":["Squeaky-Voiced Teen","Willie"],"edge":43,"y":0.0443257869,"source":"Squeaky-Voiced Teen"},{"target":"The Rich Texan","weight":1,"x":-0.1541793434,"pair":["Burns","The Rich Texan"],"edge":44,"y":0.2335578491,"source":"Burns"},{"target":"The Rich Texan","weight":1,"x":-0.2793230182,"pair":["Burns","The Rich Texan"],"edge":44,"y":0.016769962,"source":"Burns"},{"target":"Centurion Wiggum","weight":1,"x":-0.1436566403,"pair":["Caligatus Lou","Centurion Wiggum"],"edge":45,"y":0.1626771545,"source":"Caligatus Lou"},{"target":"Centurion Wiggum","weight":1,"x":-0.3834668106,"pair":["Caligatus Lou","Centurion Wiggum"],"edge":45,"y":0.0909079904,"source":"Caligatus Lou"},{"target":"Matthew (begins writing)","weight":1,"x":-0.1436566403,"pair":["Caligatus Lou","Matthew (begins writing)"],"edge":46,"y":0.1626771545,"source":"Caligatus Lou"},{"target":"Matthew (begins writing)","weight":1,"x":-0.2013958843,"pair":["Caligatus Lou","Matthew (begins writing)"],"edge":46,"y":-0.080876876,"source":"Caligatus Lou"},{"target":"Matthew (begins writing)","weight":1,"x":-0.3834668106,"pair":["Centurion Wiggum","Matthew (begins writing)"],"edge":47,"y":0.0909079904,"source":"Centurion Wiggum"},{"target":"Matthew (begins writing)","weight":1,"x":-0.2013958843,"pair":["Centurion Wiggum","Matthew (begins writing)"],"edge":47,"y":-0.080876876,"source":"Centurion Wiggum"},{"target":"Second Officer Milhouse","weight":1,"x":-0.1906239461,"pair":["Captain Seymour Bligh","Second Officer Milhouse"],"edge":48,"y":0.1037126907,"source":"Captain Seymour Bligh"},{"target":"Second Officer Milhouse","weight":1,"x":-0.3914171169,"pair":["Captain Seymour Bligh","Second Officer Milhouse"],"edge":48,"y":-0.0457589705,"source":"Captain Seymour Bligh"},{"target":"Seymour Bligh","weight":1,"x":-0.1906239461,"pair":["Captain Seymour Bligh","Seymour Bligh"],"edge":49,"y":0.1037126907,"source":"Captain Seymour Bligh"},{"target":"Seymour Bligh","weight":1,"x":-0.1615674455,"pair":["Captain Seymour Bligh","Seymour Bligh"],"edge":49,"y":-0.1448999177,"source":"Captain Seymour Bligh"},{"target":"Seymour Bligh","weight":1,"x":-0.3914171169,"pair":["Second Officer Milhouse","Seymour Bligh"],"edge":50,"y":-0.0457589705,"source":"Second Officer Milhouse"},{"target":"Seymour Bligh","weight":1,"x":-0.1615674455,"pair":["Second Officer Milhouse","Seymour Bligh"],"edge":50,"y":-0.1448999177,"source":"Second Officer Milhouse"},{"target":"Patty","weight":1,"x":-0.8554112714,"pair":["Charles","Patty"],"edge":51,"y":0.1022431083,"source":"Charles"},{"target":"Patty","weight":1,"x":-0.5635564709,"pair":["Charles","Patty"],"edge":51,"y":0.0422373335,"source":"Charles"},{"target":"Verity","weight":1,"x":-0.8554112714,"pair":["Charles","Verity"],"edge":52,"y":0.1022431083,"source":"Charles"},{"target":"Verity","weight":1,"x":-0.6684573204,"pair":["Charles","Verity"],"edge":52,"y":-0.0743856409,"source":"Charles"},{"target":"Verity","weight":1,"x":-0.5635564709,"pair":["Patty","Verity"],"edge":53,"y":0.0422373335,"source":"Patty"},{"target":"Verity","weight":1,"x":-0.6684573204,"pair":["Patty","Verity"],"edge":53,"y":-0.0743856409,"source":"Patty"},{"target":"Lindsay Nagel","weight":1,"x":-0.159041871,"pair":["Edna Krabappel","Lindsay Nagel"],"edge":54,"y":-0.078768206,"source":"Edna Krabappel"},{"target":"Lindsay Nagel","weight":1,"x":-0.2549354069,"pair":["Edna Krabappel","Lindsay Nagel"],"edge":54,"y":-0.2696951774,"source":"Edna Krabappel"},{"target":"Principal Skinner [phonily]","weight":1,"x":-0.159041871,"pair":["Edna Krabappel","Principal Skinner [phonily]"],"edge":55,"y":-0.078768206,"source":"Edna Krabappel"},{"target":"Principal Skinner [phonily]","weight":1,"x":-0.0640089364,"pair":["Edna Krabappel","Principal Skinner [phonily]"],"edge":55,"y":-0.3655879438,"source":"Edna Krabappel"},{"target":"Skinner","weight":1,"x":-0.159041871,"pair":["Edna Krabappel","Skinner"],"edge":56,"y":-0.078768206,"source":"Edna Krabappel"},{"target":"Skinner","weight":1,"x":0.0318833635,"pair":["Edna Krabappel","Skinner"],"edge":56,"y":-0.1746606815,"source":"Edna Krabappel"},{"target":"Principal Skinner [phonily]","weight":1,"x":-0.2549354069,"pair":["Lindsay Nagel","Principal Skinner [phonily]"],"edge":57,"y":-0.2696951774,"source":"Lindsay Nagel"},{"target":"Principal Skinner [phonily]","weight":1,"x":-0.0640089364,"pair":["Lindsay Nagel","Principal Skinner [phonily]"],"edge":57,"y":-0.3655879438,"source":"Lindsay Nagel"},{"target":"Skinner","weight":1,"x":-0.2549354069,"pair":["Lindsay Nagel","Skinner"],"edge":58,"y":-0.2696951774,"source":"Lindsay Nagel"},{"target":"Skinner","weight":1,"x":0.0318833635,"pair":["Lindsay Nagel","Skinner"],"edge":58,"y":-0.1746606815,"source":"Lindsay Nagel"},{"target":"Skinner","weight":1,"x":-0.0640089364,"pair":["Principal Skinner [phonily]","Skinner"],"edge":59,"y":-0.3655879438,"source":"Principal Skinner [phonily]"},{"target":"Skinner","weight":1,"x":0.0318833635,"pair":["Principal Skinner [phonily]","Skinner"],"edge":59,"y":-0.1746606815,"source":"Principal Skinner [phonily]"},{"target":"Nelson","weight":1,"x":0.7231527304,"pair":["Lisa","Nelson"],"edge":60,"y":-0.5346928239,"source":"Lisa"},{"target":"Nelson","weight":1,"x":0.7608167771,"pair":["Lisa","Nelson"],"edge":60,"y":-0.8102596189,"source":"Lisa"},{"target":"Sea Captain","weight":1,"x":0.7231527304,"pair":["Lisa","Sea Captain"],"edge":61,"y":-0.5346928239,"source":"Lisa"},{"target":"Sea Captain","weight":1,"x":1.0,"pair":["Lisa","Sea Captain"],"edge":61,"y":-0.5128946709,"source":"Lisa"},{"target":"Maid 2","weight":1,"x":0.2190661607,"pair":["Maid 1","Maid 2"],"edge":62,"y":-0.3206478041,"source":"Maid 1"},{"target":"Maid 2","weight":1,"x":0.3737909989,"pair":["Maid 1","Maid 2"],"edge":62,"y":-0.2963213474,"source":"Maid 1"},{"target":"Maids","weight":1,"x":0.2190661607,"pair":["Maid 1","Maids"],"edge":63,"y":-0.3206478041,"source":"Maid 1"},{"target":"Maids","weight":1,"x":0.401681731,"pair":["Maid 1","Maids"],"edge":63,"y":-0.1374691437,"source":"Maid 1"},{"target":"Maids","weight":1,"x":0.3737909989,"pair":["Maid 2","Maids"],"edge":64,"y":-0.2963213474,"source":"Maid 2"},{"target":"Maids","weight":1,"x":0.401681731,"pair":["Maid 2","Maids"],"edge":64,"y":-0.1374691437,"source":"Maid 2"},{"target":"Rod","weight":1,"x":0.1268148764,"pair":["Ned","Rod"],"edge":65,"y":-0.3190173253,"source":"Ned"},{"target":"Rod","weight":1,"x":0.2553269392,"pair":["Ned","Rod"],"edge":65,"y":-0.1010750738,"source":"Ned"},{"target":"Todd","weight":1,"x":0.1268148764,"pair":["Ned","Todd"],"edge":66,"y":-0.3190173253,"source":"Ned"},{"target":"Todd","weight":1,"x":0.0023714197,"pair":["Ned","Todd"],"edge":66,"y":-0.1026591181,"source":"Ned"},{"target":"Ned Flanders","weight":1,"x":0.2553269392,"pair":["Rod","Ned Flanders"],"edge":67,"y":-0.1010750738,"source":"Rod"},{"target":"Ned Flanders","weight":1,"x":0.4766530182,"pair":["Rod","Ned Flanders"],"edge":67,"y":0.02543667,"source":"Rod"},{"target":"Todd","weight":1,"x":0.2553269392,"pair":["Rod","Todd"],"edge":68,"y":-0.1010750738,"source":"Rod"},{"target":"Todd","weight":1,"x":0.0023714197,"pair":["Rod","Todd"],"edge":68,"y":-0.1026591181,"source":"Rod"},{"target":"Quimby's Nephew","weight":1,"x":0.2247603238,"pair":["Quimby","Quimby's Nephew"],"edge":69,"y":-0.166760103,"source":"Quimby"},{"target":"Quimby's Nephew","weight":1,"x":0.2682269441,"pair":["Quimby","Quimby's Nephew"],"edge":69,"y":0.0797526725,"source":"Quimby"}]